{
  "/DYJetsToLL_M-50_TuneCUETP8M1_13TeV-madgraphMLM-pythia8/": {
    "files": {
      "/local/cms/user/poczo001/WrCoffea/datasets/95537AFE-1978-A847-A49E-5ABDE5F9D8B5.root": {
        "object_path": "Events",
        "steps": [
          [
            0,
            101871
          ],
          [
            101871,
            203742
          ],
          [
            203742,
            305613
          ],
          [
            305613,
            407484
          ],
          [
            407484,
            509355
          ],
          [
            509355,
            611226
          ],
          [
            611226,
            713097
          ],
          [
            713097,
            814968
          ],
          [
            814968,
            916839
          ],
          [
            916839,
            1018710
          ],
          [
            1018710,
            1120581
          ],
          [
            1120581,
            1222452
          ],
          [
            1222452,
            1324323
          ],
          [
            1324323,
            1426194
          ],
          [
            1426194,
            1528065
          ],
          [
            1528065,
            1629936
          ],
          [
            1629936,
            1731807
          ],
          [
            1731807,
            1833678
          ],
          [
            1833678,
            1935545
          ]
        ],
        "num_entries": 1935545,
        "uuid": "ae6d5cdc-ed70-11eb-833d-29060d0abeef"
      }
    },
    "metadata": {
      "mc_campaign": "UL2018",
      "process": "DYJets",
      "dataset": "DYJetsToLL_M-50",
      "xsec": 6077.22
    },
    "form": null
  }
}